blossoms_sayak/__init__.py
blossoms_sayak/geometry.py
blossoms_sayak/operations.py
blossoms_sayak/py.typed
blossoms_sayak-0.17.0.dist-info/METADATA
blossoms_sayak-0.17.0.dist-info/WHEEL
blossoms_sayak-0.17.0.dist-info/top_level.txt
blossoms_sayak-0.17.0.dist-info/RECORD
