Metadata-Version: 2.1
Name: blossoms_sayak
Version: 0.17.0
Summary: A simple Python package for math operations and geometry calculations.
Author: Sayak Paul
Author-email: spsayakpaul@gmail.com
Classifier: Programming Language :: Python :: 3
Classifier: License :: OSI Approved :: MIT License
Classifier: Operating System :: OS Independent
Requires-Python: >=3.8
